./clocker.py
clocker-0.1.dist-info/METADATA
clocker-0.1.dist-info/WHEEL
clocker-0.1.dist-info/RECORD
