Metadata-Version: 1.2
Name: clocker
Version: 0.1
Summary: A small Python 3 module that keeps track of elapsed time
Home-page: https://github.com/Fuchida/clocker
License: UNKNOWN
Author: Abdul Salim
Author-email: abdul@bhream.com
Classifier: License :: OSI Approved :: MIT License
